{"compat":{"partially-supported":[],"unsupported":[]},"interactive-example":"https://interactive-examples.mdn.mozilla.net/pages/css/clear.html","name":"clear","see-also":[{"target":"https://developer.mozilla.org/en-US/docs/Web/CSS/CSS_box_model/Introduction_to_the_CSS_box_model","text":"CSS basic box model"}],"status":[],"summary":"The <strong><code>clear</code></strong> <a href=\"https://developer.mozilla.org/en-US/docs/Web/CSS\">CSS</a> property sets whether an element must be moved below (cleared) <a href=\"https://developer.mozilla.org/en-US/docs/Web/CSS/float\">floating</a> elements that precede it. The <code>clear</code> property applies to floating and non-floating elements.","syntax-example":"/* Keyword values */\nclear: none;\nclear: left;\nclear: right;\nclear: both;\nclear: inline-start;\nclear: inline-end;\n\n/* Global values */\nclear: inherit;\nclear: initial;\nclear: revert;\nclear: revert-layer;\nclear: unset;\n"}