{"compat":{"partially-supported":[],"unsupported":[]},"interactive-example":"https://interactive-examples.mdn.mozilla.net/pages/css/page-break-before.html","name":"page-break-before","see-also":[{"target":"https://developer.mozilla.org/en-US/docs/Web/CSS/break-before","text":"break-before"},{"target":"https://developer.mozilla.org/en-US/docs/Web/CSS/page-break-after","text":"page-break-after"},{"target":"https://developer.mozilla.org/en-US/docs/Web/CSS/orphans","text":"orphans"}],"status":[],"summary":"The <strong><code>page-break-before</code></strong> CSS property adjusts page breaks <em>before</em> the current element.","syntax-example":"/* Keyword values */\npage-break-before: auto;\npage-break-before: always;\npage-break-before: avoid;\npage-break-before: left;\npage-break-before: right;\npage-break-before: recto;\npage-break-before: verso;\n\n/* Global values */\npage-break-before: inherit;\npage-break-before: initial;\npage-break-before: revert;\npage-break-before: revert-layer;\npage-break-before: unset;\n"}