{"compat":{"partially-supported":[],"unsupported":[]},"interactive-example":"https://interactive-examples.mdn.mozilla.net/pages/css/resize.html","name":"resize","see-also":[{"target":"https://developer.mozilla.org/en-US/docs/Web/HTML/Element/textarea","text":"&lt;textarea&gt;"}],"status":[],"summary":"The <strong><code>resize</code></strong> <a href=\"https://developer.mozilla.org/en-US/docs/Web/CSS\">CSS</a> property sets whether an element is resizable, and if so, in which directions.","syntax-example":"/* Keyword values */\nresize: none;\nresize: both;\nresize: horizontal;\nresize: vertical;\nresize: block;\nresize: inline;\n\n/* Global values */\nresize: inherit;\nresize: initial;\nresize: revert;\nresize: revert-layer;\nresize: unset;\n"}