{"compat":{"partially-supported":[],"unsupported":["Firefox","Firefox for Android"]},"name":"widows","see-also":[{"target":"https://developer.mozilla.org/en-US/docs/Web/CSS/orphans","text":"orphans"},{"target":"https://developer.mozilla.org/en-US/docs/Web/CSS/CSS_paged_media","text":"Paged media"}],"status":[],"summary":"The <strong><code>widows</code></strong> <a href=\"https://developer.mozilla.org/en-US/docs/Web/CSS\">CSS</a> property sets the minimum number of lines in a block container that must be shown at the <em>top</em> of a <a href=\"https://developer.mozilla.org/en-US/docs/Web/CSS/CSS_paged_media\">page</a>, region, or <a href=\"https://developer.mozilla.org/en-US/docs/Web/CSS/CSS_multicol_layout\">column</a>.","syntax-example":"/* &lt;integer&gt; values */\nwidows: 2;\nwidows: 3;\n\n/* Global values */\nwidows: inherit;\nwidows: initial;\nwidows: revert;\nwidows: revert-layer;\nwidows: unset;\n"}